seadexarr/__init__.py
seadexarr/modules/__init__.py
seadexarr/modules/anilist.py
seadexarr/modules/cli.py
seadexarr/modules/config_sample.yml
seadexarr/modules/discord.py
seadexarr/modules/log.py
seadexarr/modules/seadex_arr.py
seadexarr/modules/seadex_radarr.py
seadexarr/modules/seadex_sonarr.py
seadexarr/modules/torrent.py
seadexarr-0.9.0.dist-info/licenses/LICENSE
seadexarr-0.9.0.dist-info/METADATA
seadexarr-0.9.0.dist-info/WHEEL
seadexarr-0.9.0.dist-info/entry_points.txt
seadexarr-0.9.0.dist-info/top_level.txt
seadexarr-0.9.0.dist-info/RECORD
