Metadata-Version: 2.4
Name: seadexarr
Version: 0.9.0
Summary: SeaDex Starr Sync
Author: bbtufty
Maintainer: bbtufty
License:                     GNU GENERAL PUBLIC LICENSE
Project-URL: Homepage, https://github.com/bbtufty/seadexarr
Project-URL: Bug Reports, https://github.com/bbtufty/seadexarr/issues
Project-URL: Source, https://github.com/bbtufty/seadexarr
Classifier: Development Status :: 4 - Beta
Classifier: License :: OSI Approved :: GNU General Public License v3 or later (GPLv3+)
Classifier: Programming Language :: Python
Classifier: Programming Language :: Python :: 3
Classifier: Programming Language :: Python :: 3.11
Classifier: Programming Language :: Python :: 3.12
Classifier: Programming Language :: Python :: 3 :: Only
Requires-Python: >=3.11
License-File: LICENSE
Requires-Dist: arrapi==1.4.14
Requires-Dist: beautifulsoup4==4.13.5
Requires-Dist: colorlog==6.9.0
Requires-Dist: discordwebhook==1.0.3
Requires-Dist: httpx==0.28.1
Requires-Dist: pynyaa==2.0.0
Requires-Dist: PyYAML==6.0.2
Requires-Dist: qbittorrent-api==2025.7.0
Requires-Dist: requests==2.32.5
Requires-Dist: ruamel.yaml==0.18.15
Requires-Dist: seadex==0.7.2
Requires-Dist: typer==0.17.4
Provides-Extra: docs
Requires-Dist: sphinx-automodapi==0.20.0; extra == "docs"
Requires-Dist: sphinx-rtd-theme==3.0.2; extra == "docs"
Dynamic: license-file
